README.rst
setup.py
sprintero/__init__.py
sprintero/commands.py
sprintero/constants.py
sprintero/generator.py
sprintero/main.py
sprintero.egg-info/PKG-INFO
sprintero.egg-info/SOURCES.txt
sprintero.egg-info/dependency_links.txt
sprintero.egg-info/entry_points.txt
sprintero.egg-info/requires.txt
sprintero.egg-info/top_level.txt
sprintero/names_collection/__init__.py
sprintero/names_collection/base.py
sprintero/names_collection/picker.py
sprintero/names_collection/marvel/__init__.py
sprintero/names_collection/marvel/collection.py
sprintero/names_collection/marvel/rightful.data
sprintero/names_collection/marvel/vicious.data