Metadata-Version: 1.0
Name: sprintero
Version: 0.1.2
Summary: Sprint name generator
Home-page: https://github.com/opalczynski/sprintero
Author: Sebastian Opalczynski
Author-email: opalczynski@gmail.com
License: MIT
Platform: UNKNOWN
